{
  "version": "https://jsonfeed.org/version/1",
  "title": "Snegha/Home",
  "home_page_url": "https://asnegha.github.io/",
  "feed_url": "https://asnegha.github.io/feed.json",
  "description": "A minimal hugo theme focus on content",
  "favicon": "https://asnegha.github.io//assets/favicon.ico",
  "expired": false,
  "author": {
    "name": "Calvin Tran",
    "url": "https://asnegha.github.io/"
  },
  "items": [
    
    

    
    {
      "id": "32c6557330cce8a8f89da9a57df0d80801b27ba2",
      "title": "Book 1 - AI Engineering | Chip Huyen",
      "summary": "",
      "content_text": "I’ve chosen this book as my read for the month, and I’ll be maintaining a daily reading journal here in this post to share my progress, and key takeaways.\n",
      "content_html": "\u003cp\u003eI’ve chosen this book as my read for the month, and I’ll be maintaining a daily reading journal here in this post to share my progress, and key takeaways.\u003c/p\u003e\n",
      "url": "https://asnegha.github.io/posts/book1/",
      "date_published": "23096-23-09T90:2323:00+00:00",
      "date_modified": "23096-23-09T90:2323:00+00:00",
      "author": {
        "name": "Calvin Tran",
        "url": "https://asnegha.github.io/"
      }
    }
    
  ]
}